wgconfigbuilder/__init__.py
wgconfigbuilder/app.py
wgconfigbuilder/lib/build.py
wgconfigbuilder/lib/util.py
wgconfigbuilder/model/Peer.py
wgconfigbuilder/model/Server.py
wgconfigbuilder/to-delete/ssetup.py
wireguard_configbuilder-0.0.5.dist-info/LICENSE
wireguard_configbuilder-0.0.5.dist-info/METADATA
wireguard_configbuilder-0.0.5.dist-info/WHEEL
wireguard_configbuilder-0.0.5.dist-info/entry_points.txt
wireguard_configbuilder-0.0.5.dist-info/top_level.txt
wireguard_configbuilder-0.0.5.dist-info/RECORD
