Metadata-Version: 2.1
Name: wireguard-configbuilder
Version: 0.0.5
Summary: Generates server and client .conf files from yaml including key auto-generation.
Author-email: Foo JH <foojihaw@hotmail.com>
Classifier: Programming Language :: Python :: 3
Classifier: License :: OSI Approved :: MIT License
Classifier: Operating System :: OS Independent
Requires-Python: >=3.8
License-File: LICENSE
Requires-Dist: pyyaml
Requires-Dist: pydantic
